brainstate/__init__.py
brainstate/_compatible_import.py
brainstate/_compatible_import_test.py
brainstate/_deprecation.py
brainstate/_deprecation_test.py
brainstate/_error.py
brainstate/_state.py
brainstate/_state_global_hooks.py
brainstate/_state_hook_context.py
brainstate/_state_hook_core.py
brainstate/_state_hook_manager.py
brainstate/_state_hook_manager_test.py
brainstate/_state_hooks_test.py
brainstate/_state_test.py
brainstate/_state_thread_safety_test.py
brainstate/_utils.py
brainstate/environ.py
brainstate/environ_test.py
brainstate/mixin.py
brainstate/mixin_test.py
brainstate/typing.py
brainstate/typing_test.py
brainstate/graph/__init__.py
brainstate/graph/_context.py
brainstate/graph/_context_test.py
brainstate/graph/_convert.py
brainstate/graph/_node.py
brainstate/graph/_node_test.py
brainstate/graph/_operation.py
brainstate/graph/_operation_test.py
brainstate/nn/__init__.py
brainstate/nn/_activations.py
brainstate/nn/_activations_test.py
brainstate/nn/_collective_ops.py
brainstate/nn/_collective_ops_test.py
brainstate/nn/_common.py
brainstate/nn/_common_test.py
brainstate/nn/_conv.py
brainstate/nn/_conv_test.py
brainstate/nn/_delay.py
brainstate/nn/_delay_test.py
brainstate/nn/_dropout.py
brainstate/nn/_dropout_test.py
brainstate/nn/_dynamics.py
brainstate/nn/_dynamics_test.py
brainstate/nn/_elementwise.py
brainstate/nn/_elementwise_test.py
brainstate/nn/_embedding.py
brainstate/nn/_embedding_test.py
brainstate/nn/_event_fixedprob.py
brainstate/nn/_event_fixedprob_test.py
brainstate/nn/_event_linear.py
brainstate/nn/_event_linear_test.py
brainstate/nn/_exp_euler.py
brainstate/nn/_exp_euler_test.py
brainstate/nn/_hidata.py
brainstate/nn/_hidata_test.py
brainstate/nn/_linear.py
brainstate/nn/_linear_test.py
brainstate/nn/_metrics.py
brainstate/nn/_metrics_test.py
brainstate/nn/_module.py
brainstate/nn/_module_test.py
brainstate/nn/_normalizations.py
brainstate/nn/_normalizations_test.py
brainstate/nn/_paddings.py
brainstate/nn/_paddings_test.py
brainstate-0.2.10.dist-info/licenses/LICENSE
brainstate-0.2.10.dist-info/METADATA
brainstate-0.2.10.dist-info/WHEEL
brainstate-0.2.10.dist-info/top_level.txt
brainstate-0.2.10.dist-info/RECORD
