Metadata-Version: 2.4
Name: brainstate
Version: 0.2.10
Summary: A State-based Transformation System for Brain Modeling.
Author-email: BrainState Developers <chao.brain@qq.com>
Project-URL: homepage, https://github.com/chaobrain/brainstate
Project-URL: repository, https://github.com/chaobrain/brainstate
Project-URL: Documentation, https://brainstate.readthedocs.io/
Project-URL: Source Code, https://github.com/chaobrain/brainstate
Project-URL: Bug Tracker, https://github.com/chaobrain/brainstate/issues
Keywords: computational neuroscience,brain-inspired computing,brain simulation,brain modeling,spiking neural networks
Classifier: Natural Language :: English
Classifier: Operating System :: OS Independent
Classifier: Development Status :: 4 - Beta
Classifier: Intended Audience :: Developers
Classifier: Intended Audience :: Science/Research
Classifier: Programming Language :: Python :: 3
Classifier: Programming Language :: Python :: 3.10
Classifier: Programming Language :: Python :: 3.11
Classifier: Programming Language :: Python :: 3.12
Classifier: Programming Language :: Python :: 3.13
Classifier: Programming Language :: Python :: 3.14
Classifier: Programming Language :: Python
Classifier: Topic :: Scientific/Engineering :: Bio-Informatics
Classifier: Topic :: Scientific/Engineering :: Mathematics
Classifier: Topic :: Scientific/Engineering :: Artificial Intelligence
Classifier: Topic :: Software Development :: Libraries
Requires-Python: >=3.10
License-File: LICENSE
Requires-Dist: numpy>=1.15
Requires-Dist: tqdm
Requires-Dist: brainunit
Requires-Dist: brainevent
Provides-Extra: cpu
Requires-Dist: jax[cpu]; extra == "cpu"
Requires-Dist: brainunit; extra == "cpu"
Requires-Dist: brainevent; extra == "cpu"
Provides-Extra: cuda12
Requires-Dist: jax[cuda12]; extra == "cuda12"
Requires-Dist: brainunit; extra == "cuda12"
Requires-Dist: brainevent; extra == "cuda12"
Provides-Extra: cuda13
Requires-Dist: jax[cuda13]; extra == "cuda13"
Requires-Dist: brainunit; extra == "cuda13"
Requires-Dist: brainevent; extra == "cuda13"
Provides-Extra: tpu
Requires-Dist: jax[tpu]; extra == "tpu"
Requires-Dist: brainunit; extra == "tpu"
Requires-Dist: brainevent; extra == "tpu"
Provides-Extra: testing
Requires-Dist: absl-py; extra == "testing"
Requires-Dist: pytest; extra == "testing"
Requires-Dist: jax; extra == "testing"
Requires-Dist: brainunit; extra == "testing"
Requires-Dist: brainevent; extra == "testing"
Dynamic: license-file
